awswl/VERSION
awswl/__init__.py
awswl/cli.py
awswl/commands.py
awswl/externalip.py
awswl/main.py
awswl-1.2.1.dist-info/LICENSE.txt
awswl-1.2.1.dist-info/METADATA
awswl-1.2.1.dist-info/WHEEL
awswl-1.2.1.dist-info/entry_points.txt
awswl-1.2.1.dist-info/RECORD
