Metadata-Version: 2.1
Name: awswl
Version: 1.2.1
Summary: A project to make it simple to add/remove ip addresses (or CIDR blocks) from an AWS Security group.
Home-page: https://github.com/geoffreywiseman/awswl
License: Public Domain
Keywords: aws,vpn,securitygroups,security,networking,allowlist,ssh,firewall,utility
Author: Geoffrey Wiseman
Author-email: geoffrey.wiseman@codiform.com
Requires-Python: >=3.9,<4.0
Classifier: Development Status :: 5 - Production/Stable
Classifier: Intended Audience :: Developers
Classifier: License :: Other/Proprietary License
Classifier: License :: Public Domain
Classifier: Programming Language :: Python :: 3
Classifier: Programming Language :: Python :: 3.9
Classifier: Programming Language :: Python :: 3.10
Classifier: Programming Language :: Python :: 3.11
Classifier: Programming Language :: Python :: 3.12
Classifier: Programming Language :: Python :: 3.13
Classifier: Topic :: System :: Networking
Classifier: Topic :: System :: Networking :: Firewalls
Requires-Dist: boto3 (>=1.35.62,<2.0.0)
Requires-Dist: ipaddress (>=1.0.23,<2.0.0)
Requires-Dist: requests (==2.32.3)
Requires-Dist: urllib3 (<2)
Requires-Dist: usingversion (>=0.1.2,<0.2.0)
Project-URL: Repository, https://github.com/geoffreywiseman/awswl
